codegraph_mcp/__init__.py
codegraph_mcp/analysis.py
codegraph_mcp/ast_parser.py
codegraph_mcp/builder.py
codegraph_mcp/context.py
codegraph_mcp/docs.py
codegraph_mcp/neo4j_client.py
codegraph_mcp/queries.py
codegraph_mcp/scanner.py
codegraph_mcp/schema.py
codegraph_mcp/updater.py
codegraph_mcp/watcher.py
codegraph_mcp/custom/__init__.py
codegraph_mcp/custom/domo_visitor.py
codegraph_mcp/custom/entity_analyzer.py
codegraph_mcp/custom/mcp_analyzer.py
codegraph_mcp/custom/route_analyzer.py
codegraph_mcp/custom/test_analyzer.py
codegraph_mcp/mcp_server/__init__.py
codegraph_mcp/mcp_server/__main__.py
codegraph_mcp/mcp_server/server.py
codegraph_mcp/mcp_server/resources/__init__.py
codegraph_mcp/mcp_server/resources/codegraph.py
codegraph_mcp/mcp_server/tools/__init__.py
codegraph_mcp/mcp_server/tools/codegraph.py
codegraph_mcp/scripts/build-codegraph.py
domo_mcp/__init__.py
domo_mcp/__main__.py
domo_mcp/auth_context.py
domo_mcp/server.py
domo_mcp/prompts/__init__.py
domo_mcp/prompts/operations.py
domo_mcp/resources/__init__.py
domo_mcp/resources/categories.py
domo_mcp/resources/codegraph.py
domo_mcp/resources/entities.py
domo_mcp/tools/__init__.py
domo_mcp/tools/access_tokens.py
domo_mcp/tools/codegraph.py
domo_mcp/tools/dataflows.py
domo_mcp/tools/datasets.py
domo_mcp/tools/groups.py
domo_mcp/tools/pages.py
domo_mcp/tools/roles.py
domo_mcp/tools/users.py
domolibrary2/__init__.py
domolibrary2/_modidx.py
domolibrary2/auth/__init__.py
domolibrary2/auth/base.py
domolibrary2/auth/developer.py
domolibrary2/auth/full.py
domolibrary2/auth/jupyter.py
domolibrary2/auth/token.py
domolibrary2/auth/utils.py
domolibrary2/base/__init__.py
domolibrary2/base/base.py
domolibrary2/base/entities.py
domolibrary2/base/entities_federated.py
domolibrary2/base/exceptions.py
domolibrary2/base/publish_resolver.py
domolibrary2/base/relationships.py
domolibrary2/classes/DomoAppDb.py
domolibrary2/classes/DomoAppStudio.py
domolibrary2/classes/DomoAppStudio_publish.py
domolibrary2-2.4.1.dist-info/licenses/LICENSE
domolibrary2-2.4.1.dist-info/METADATA
domolibrary2-2.4.1.dist-info/WHEEL
domolibrary2-2.4.1.dist-info/top_level.txt
domolibrary2-2.4.1.dist-info/RECORD
