Metadata-Version: 2.4
Name: domolibrary2
Version: 2.4.1
Summary: A Python library for interacting with Domo APIs
Author-email: Jae Wilson <jaewilson07@gmail.com>
License-Expression: Apache-2.0
Keywords: jupyter,notebook,python,domo,api
Classifier: Development Status :: 3 - Alpha
Classifier: Intended Audience :: Developers
Classifier: Natural Language :: English
Classifier: Programming Language :: Python :: 3.13
Requires-Python: >=3.13
License-File: LICENSE
Requires-Dist: pandas
Requires-Dist: aiohttp
Requires-Dist: dc-logger>=1.2.0
Requires-Dist: requests
Requires-Dist: twine
Requires-Dist: orjson
Requires-Dist: httpx
Requires-Dist: python-dotenv
Requires-Dist: sqlparse
Requires-Dist: sqlglot
Requires-Dist: bs4
Requires-Dist: nbqa
Requires-Dist: black
Requires-Dist: aenum
Requires-Dist: pillow
Requires-Dist: xkcdpass
Requires-Dist: sql_metadata
Requires-Dist: beautifulsoup4
Requires-Dist: IPython
Provides-Extra: dev
Requires-Dist: pytest; extra == "dev"
Requires-Dist: pytest-asyncio; extra == "dev"
Requires-Dist: bandit; extra == "dev"
Requires-Dist: pylint; extra == "dev"
Requires-Dist: ruff; extra == "dev"
Requires-Dist: black; extra == "dev"
Requires-Dist: isort; extra == "dev"
Requires-Dist: mypy; extra == "dev"
Requires-Dist: pytest-cov; extra == "dev"
Requires-Dist: pre-commit; extra == "dev"
Provides-Extra: postman
Requires-Dist: requests; extra == "postman"
Requires-Dist: pydantic-ai; extra == "postman"
Requires-Dist: langgraph; extra == "postman"
Provides-Extra: mcp
Requires-Dist: fastmcp; extra == "mcp"
Requires-Dist: pydantic>=2.0; extra == "mcp"
Provides-Extra: codegraph-mcp
Requires-Dist: neo4j>=5.0.0; extra == "codegraph-mcp"
Requires-Dist: watchdog>=3.0.0; extra == "codegraph-mcp"
Requires-Dist: fastmcp; extra == "codegraph-mcp"
Provides-Extra: password-manager
Requires-Dist: keeper-secrets-manager-core; extra == "password-manager"
Dynamic: license-file
